devcovenant/README.md
devcovenant/__init__.py
devcovenant/__main__.py
devcovenant/cli.py
devcovenant/registry.json
devcovenant/common_policy_patches/README.md
devcovenant/common_policy_patches/__init__.py
devcovenant/core/__init__.py
devcovenant/core/base.py
devcovenant/core/engine.py
devcovenant/core/install.py
devcovenant/core/parser.py
devcovenant/core/policy_locations.py
devcovenant/core/policy_texts.py
devcovenant/core/registry.py
devcovenant/core/selectors.py
devcovenant/core/uninstall.py
devcovenant/core/update_hashes.py
devcovenant/core/fixers/__init__.py
devcovenant/core/fixers/dependency_license_sync.py
devcovenant/core/fixers/last_updated_placement.py
devcovenant/core/fixers/no_future_dates.py
devcovenant/core/fixers/raw_string_escapes.py
devcovenant/core/hooks/pre_commit.py
devcovenant/core/policy_scripts/__init__.py
devcovenant/core/policy_scripts/changelog_coverage.py
devcovenant/core/policy_scripts/dependency_license_sync.py
devcovenant/core/policy_scripts/devcov_self_enforcement.py
devcovenant/core/policy_scripts/devcov_structure_guard.py
devcovenant/core/policy_scripts/devflow_run_gates.py
devcovenant/core/policy_scripts/docstring_and_comment_coverage.py
devcovenant/core/policy_scripts/documentation_growth_tracking.py
devcovenant/core/policy_scripts/gcv_script_naming.py
devcovenant/core/policy_scripts/last_updated_placement.py
devcovenant/core/policy_scripts/line_length_limit.py
devcovenant/core/policy_scripts/managed_bench.py
devcovenant/core/policy_scripts/name_clarity.py
devcovenant/core/policy_scripts/new_modules_need_tests.py
devcovenant/core/policy_scripts/no_future_dates.py
devcovenant/core/policy_scripts/patches_txt_sync.py
devcovenant/core/policy_scripts/policy_text_presence.py
devcovenant/core/policy_scripts/raw_string_escapes.py
devcovenant/core/policy_scripts/read_only_directories.py
devcovenant/core/policy_scripts/security_compliance_notes.py
devcovenant/core/policy_scripts/security_scanner.py
devcovenant-0.2.5.dist-info/licenses/LICENSE
devcovenant-0.2.5.dist-info/METADATA
devcovenant-0.2.5.dist-info/WHEEL
devcovenant-0.2.5.dist-info/entry_points.txt
devcovenant-0.2.5.dist-info/top_level.txt
devcovenant-0.2.5.dist-info/RECORD
