Metadata-Version: 2.4
Name: devcovenant
Version: 0.2.5
Summary: Self-enforcing development policy engine
Requires-Python: >=3.10
License-File: LICENSE
Requires-Dist: PyYAML>=6.0.2
Requires-Dist: semver>=3.0.2
Dynamic: license-file
